[{"inputs":[{"internalType":"address","name":"_t","type":"address"},{"internalType":"address","name":"_rd","type":"address"},{"internalType":"address","name":"_sd","type":"address"},{"internalType":"address","name":"_acc","type":"address"}],"payable":false,"stateMutability":"nonpayable","type":"constructor"},{"anonymous":false,"inputs":[{"indexed":false,"internalType":"uint256","name":"REG_ROOT_M","type":"uint256"},{"indexed":false,"internalType":"uint256","name":"REG_SELF_SUB_M","type":"uint256"},{"indexed":false,"internalType":"uint256","name":"REG_SELF_SUB_O","type":"uint256"},{"indexed":false,"internalType":"uint256","name":"REG_NORMAL_SUB_M","type":"uint256"},{"indexed":false,"internalType":"uint256","name":"REG_NORMAL_SUB_O","type":"uint256"},{"indexed":false,"internalType":"uint256","name":"REG_CUSTOEMED_SUB_M","type":"uint256"},{"indexed":false,"internalType":"uint256","name":"REG_CUSTOEMED_SUB_O","type":"uint256"}],"name":"AllocationSetting","type":"event"},{"anonymous":false,"inputs":[{"indexed":false,"internalType":"uint256","name":"receiptID","type":"uint256"},{"indexed":false,"internalType":"address","name":"payer","type":"address"},{"indexed":false,"internalType":"bytes32","name":"nameHash","type":"bytes32"},{"indexed":false,"internalType":"uint256","name":"amount","type":"uint256"}],"name":"OperCustomerPrice","type":"event"},{"anonymous":false,"inputs":[{"indexed":false,"internalType":"uint256","name":"MAX_YEAR","type":"uint256"},{"indexed":false,"internalType":"uint256","name":"AROOT_GAS","type":"uint256"},{"indexed":false,"internalType":"uint256","name":"BROOT_GAS","type":"uint256"},{"indexed":false,"internalType":"uint256","name":"SUB_GAS","type":"uint256"},{"indexed":false,"internalType":"uint256","name":"CUSTOMED_PRICE_GAS","type":"uint256"}],"name":"PriceSetting","type":"event"},{"anonymous":false,"inputs":[{"indexed":false,"internalType":"uint256","name":"receiptID","type":"uint256"},{"indexed":false,"internalType":"address","name":"payer","type":"address"},{"indexed":true,"internalType":"bytes32","name":"nameHash","type":"bytes32"},{"indexed":false,"internalType":"uint256","name":"amount","type":"uint256"},{"indexed":false,"internalType":"bool","name":"isRoot","type":"bool"},{"indexed":false,"internalType":"bool","name":"isRare","type":"bool"}],"name":"Recharge","type":"event"},{"anonymous":false,"inputs":[{"indexed":false,"internalType":"uint256","name":"receiptID","type":"uint256"},{"indexed":false,"internalType":"address","name":"payer","type":"address"},{"indexed":false,"internalType":"bytes","name":"name","type":"bytes"},{"indexed":false,"internalType":"uint256","name":"amount","type":"uint256"},{"indexed":false,"internalType":"bool","name":"isRoot","type":"bool"},{"indexed":false,"internalType":"bool","name":"isRare","type":"bool"}],"name":"Register","type":"event"},{"constant":true,"inputs":[],"name":"AROOT_GAS","outputs":[{"internalType":"uint256","name":"","type":"uint256"}],"payable":false,"stateMutability":"view","type":"function"},{"constant":true,"inputs":[],"name":"BROOT_GAS","outputs":[{"internalType":"uint256","name":"","type":"uint256"}],"payable":false,"stateMutability":"view","type":"function"},{"constant":true,"inputs":[],"name":"CUSTOMED_PRICE_GAS","outputs":[{"internalType":"uint256","name":"","type":"uint256"}],"payable":false,"stateMutability":"view","type":"function"},{"constant":false,"inputs":[{"internalType":"address","name":"newDao","type":"address"}],"name":"ChangeDAO","outputs":[],"payable":false,"stateMutability":"nonpayable","type":"function"},{"constant":true,"inputs":[],"name":"DAOAddress","outputs":[{"internalType":"address","name":"","type":"address"}],"payable":false,"stateMutability":"view","type":"function"},{"constant":true,"inputs":[],"name":"MAX_YEAR","outputs":[{"internalType":"uint256","name":"","type":"uint256"}],"payable":false,"stateMutability":"view","type":"function"},{"constant":true,"inputs":[],"name":"REG_CUSTOEMED_SUB_M","outputs":[{"internalType":"uint256","name":"","type":"uint256"}],"payable":false,"stateMutability":"view","type":"function"},{"constant":true,"inputs":[],"name":"REG_CUSTOEMED_SUB_O","outputs":[{"internalType":"uint256","name":"","type":"uint256"}],"payable":false,"stateMutability":"view","type":"function"},{"constant":true,"inputs":[],"name":"REG_NORMAL_SUB_M","outputs":[{"internalType":"uint256","name":"","type":"uint256"}],"payable":false,"stateMutability":"view","type":"function"},{"constant":true,"inputs":[],"name":"REG_NORMAL_SUB_O","outputs":[{"internalType":"uint256","name":"","type":"uint256"}],"payable":false,"stateMutability":"view","type":"function"},{"constant":true,"inputs":[],"name":"REG_ROOT_M","outputs":[{"internalType":"uint256","name":"","type":"uint256"}],"payable":false,"stateMutability":"view","type":"function"},{"constant":true,"inputs":[],"name":"REG_SELF_SUB_M","outputs":[{"internalType":"uint256","name":"","type":"uint256"}],"payable":false,"stateMutability":"view","type":"function"},{"constant":true,"inputs":[],"name":"REG_SELF_SUB_O","outputs":[{"internalType":"uint256","name":"","type":"uint256"}],"payable":false,"stateMutability":"view","type":"function"},{"constant":true,"inputs":[],"name":"SUB_GAS","outputs":[{"internalType":"uint256","name":"","type":"uint256"}],"payable":false,"stateMutability":"view","type":"function"},{"constant":true,"inputs":[],"name":"accountant","outputs":[{"internalType":"contract BasAccountant","name":"","type":"address"}],"payable":false,"stateMutability":"view","type":"function"},{"constant":true,"inputs":[],"name":"receiptID","outputs":[{"internalType":"uint256","name":"","type":"uint256"}],"payable":false,"stateMutability":"view","type":"function"},{"constant":true,"inputs":[],"name":"rootDomainData","outputs":[{"internalType":"contract BasRootDomain","name":"","type":"address"}],"payable":false,"stateMutability":"view","type":"function"},{"constant":true,"inputs":[],"name":"subDomainData","outputs":[{"internalType":"contract BasSubDomain","name":"","type":"address"}],"payable":false,"stateMutability":"view","type":"function"},{"constant":true,"inputs":[],"name":"token","outputs":[{"internalType":"contract ERC20","name":"","type":"address"}],"payable":false,"stateMutability":"view","type":"function"},{"constant":false,"inputs":[{"internalType":"uint256","name":"max_year","type":"uint256"},{"internalType":"uint256","name":"aroot_gas","type":"uint256"},{"internalType":"uint256","name":"broot_gas","type":"uint256"},{"internalType":"uint256","name":"sub_gas","type":"uint256"},{"internalType":"uint256","name":"customed_price_gas","type":"uint256"}],"name":"priceSetting","outputs":[],"payable":false,"stateMutability":"nonpayable","type":"function"},{"constant":false,"inputs":[{"internalType":"uint256","name":"reg_root_m","type":"uint256"},{"internalType":"uint256","name":"reg_self_sub_m","type":"uint256"},{"internalType":"uint256","name":"reg_self_sub_o","type":"uint256"},{"internalType":"uint256","name":"reg_normal_sub_m","type":"uint256"},{"internalType":"uint256","name":"reg_normal_sub_o","type":"uint256"},{"internalType":"uint256","name":"reg_customed_sub_m","type":"uint256"},{"internalType":"uint256","name":"reg_customed_sub_o","type":"uint256"}],"name":"allocationSetting","outputs":[],"payable":false,"stateMutability":"nonpayable","type":"function"},{"constant":false,"inputs":[{"internalType":"address","name":"_t","type":"address"},{"internalType":"address","name":"_rd","type":"address"},{"internalType":"address","name":"_sd","type":"address"},{"internalType":"address","name":"_acc","type":"address"}],"name":"setupDataRef","outputs":[],"payable":false,"stateMutability":"nonpayable","type":"function"},{"constant":false,"inputs":[{"internalType":"bytes","name":"name","type":"bytes"},{"internalType":"bool","name":"isOpen","type":"bool"},{"internalType":"bool","name":"isCustomed","type":"bool"},{"internalType":"uint256","name":"cusPrice","type":"uint256"},{"internalType":"uint8","name":"durationInYear","type":"uint8"}],"name":"registerRoot","outputs":[],"payable":false,"stateMutability":"nonpayable","type":"function"},{"constant":false,"inputs":[{"internalType":"bytes32","name":"nameHash","type":"bytes32"},{"internalType":"uint8","name":"durationInYear","type":"uint8"}],"name":"rechargeRoot","outputs":[],"payable":false,"stateMutability":"nonpayable","type":"function"},{"constant":false,"inputs":[{"internalType":"bytes32","name":"nameHash","type":"bytes32"},{"internalType":"uint256","name":"price","type":"uint256"}],"name":"openCustomedPrice","outputs":[],"payable":false,"stateMutability":"nonpayable","type":"function"},{"constant":false,"inputs":[{"internalType":"bytes","name":"rName","type":"bytes"},{"internalType":"bytes","name":"sName","type":"bytes"},{"internalType":"uint8","name":"durationInYear","type":"uint8"}],"name":"registerSub","outputs":[],"payable":false,"stateMutability":"nonpayable","type":"function"},{"constant":false,"inputs":[{"internalType":"bytes","name":"rName","type":"bytes"},{"internalType":"bytes","name":"sName","type":"bytes"},{"internalType":"uint8","name":"durationInYear","type":"uint8"}],"name":"rechargeSub","outputs":[],"payable":false,"stateMutability":"nonpayable","type":"function"}]